setup.cfg
setup.py
foundation_platform/__init__.py
foundation_platform/command_line.py
foundation_platform.egg-info/PKG-INFO
foundation_platform.egg-info/SOURCES.txt
foundation_platform.egg-info/dependency_links.txt
foundation_platform.egg-info/top_level.txt
foundation_platform/common/__init__.py
foundation_platform/common/error.py
foundation_platform/common/keyvaluestore.py
foundation_platform/csar/__init__.py
foundation_platform/csar/csar.py
foundation_platform/csar/ingestCSAR.py
foundation_platform/messaging/__init__.py
foundation_platform/messaging/image.py
foundation_platform/messaging/restAPIClient.py
foundation_platform/vnfpi/__init__.py
foundation_platform/vnfpi/vnfpi.py
tests/__init__.py
tests/test_deploy_VNFPI.py
tests/test_test_command_line.py
tests/test_test_csar.py
tests/test_test_runner.py