Metadata-Version: 1.0
Name: foundation-platform
Version: 0.2.0
Summary: The foundation from which other NFV services are offered.
Home-page: UNKNOWN
Author: Nokia A&A Platform & Parters
Author-email: cic@nokia.com
License: UNKNOWN
Platform: UNKNOWN
